setup.py
flask_stacksentinel/__init__.py
flask_stacksentinel.egg-info/PKG-INFO
flask_stacksentinel.egg-info/SOURCES.txt
flask_stacksentinel.egg-info/dependency_links.txt
flask_stacksentinel.egg-info/requires.txt
flask_stacksentinel.egg-info/top_level.txt