Metadata-Version: 1.1
Name: flask-stacksentinel
Version: 1.2.1
Summary: Stack Sentinel error tracking integration with Flask
Home-page: https://github.com/StackSentinel/stacksentinel-flask
Author: Jeri MgCuckin
Author-email: jerymcguckin@stacksentinel.com
License: Apache License (2.0)
Platform: any
Classifier: Environment :: Web Environment
Classifier: Intended Audience :: Developers
Classifier: Operating System :: OS Independent
Classifier: Programming Language :: Python
Classifier: Programming Language :: Python :: 2
Classifier: Programming Language :: Python :: 2.7
Classifier: Programming Language :: Python :: 3
Classifier: Programming Language :: Python :: 3.4
